LICENSE.txt
MANIFEST.in
README.rst
VERSION.txt
setup.cfg
setup.py
docs/source/changelog.rst
hubspot/__init__.py
hubspot/connection/__init__.py
hubspot/connection/_validators.py
hubspot/connection/exc.py
hubspot/connection/testing.py
hubspot_connection.egg-info/PKG-INFO
hubspot_connection.egg-info/SOURCES.txt
hubspot_connection.egg-info/dependency_links.txt
hubspot_connection.egg-info/namespace_packages.txt
hubspot_connection.egg-info/pbr.json
hubspot_connection.egg-info/requires.txt
hubspot_connection.egg-info/top_level.txt