Metadata-Version: 1.1
Name: hubspot-connection
Version: 1.0rc8
Summary: Lightweight abstraction layer for making requests to the HubSpot API
Home-page: http://pythonhosted.org/hubspot-connection/
Author: 2degrees Limited
Author-email: 2degrees-floss@googlegroups.com
License: BSD (http://dev.2degreesnetwork.com/p/2degrees-license.html)
Keywords: hubspot
Platform: UNKNOWN
Classifier: Development Status :: 5 - Production/Stable
Classifier: Intended Audience :: Developers
Classifier: License :: OSI Approved :: BSD License
Classifier: Natural Language :: English
Classifier: Programming Language :: Python
